onager/__init__.py
onager/cancel.py
onager/config.py
onager/constants.py
onager/frontend.py
onager/launcher.py
onager/list.py
onager/meta_launcher.py
onager/multiworker.py
onager/subjobsfilemanager.py
onager/utils.py
onager/worker.py
onager/backends/__init__.py
onager/backends/_backend.py
onager/backends/gridengine.py
onager/backends/local.py
onager/backends/prepare_backend.py
onager/backends/slurm.py
onager-0.1.3.data/scripts/onager
onager-0.1.3.dist-info/LICENSE
onager-0.1.3.dist-info/METADATA
onager-0.1.3.dist-info/WHEEL
onager-0.1.3.dist-info/top_level.txt
onager-0.1.3.dist-info/RECORD
