Metadata-Version: 2.1
Name: onager
Version: 0.1.3
Summary: Lightweight python library for launching experiments and tuning hyperparameters, either locally or on a cluster
Home-page: https://github.com/camall3n/onager/
Author: Cameron Allen, Neev Parikh
Author-email: csal@brown.edu,neev_parikh@brown.edu
License: UNKNOWN
Platform: UNKNOWN
Classifier: Programming Language :: Python :: 3
Classifier: License :: OSI Approved :: MIT License
Classifier: Operating System :: OS Independent
License-File: LICENSE
Requires-Dist: tabulate
